tensorpool/__init__.py
tensorpool/helpers.py
tensorpool/main.py
tensorpool/spinner.py
tensorpool-5.0.2.dist-info/licenses/LICENSE
tensorpool-5.0.2.dist-info/METADATA
tensorpool-5.0.2.dist-info/WHEEL
tensorpool-5.0.2.dist-info/entry_points.txt
tensorpool-5.0.2.dist-info/top_level.txt
tensorpool-5.0.2.dist-info/RECORD
