Metadata-Version: 2.4
Name: tensorpool
Version: 5.0.2
Summary: TensorPool https://tensorpool.dev/
Author-email: Joshua Martinez <joshua@tensorpool.dev>
Classifier: Programming Language :: Python :: 3
Classifier: Programming Language :: Python :: 3.8
Classifier: Programming Language :: Python :: 3.9
Classifier: Programming Language :: Python :: 3.10
Classifier: Programming Language :: Python :: 3.11
Classifier: Intended Audience :: Developers
Classifier: Intended Audience :: Science/Research
Classifier: Intended Audience :: Information Technology
Classifier: Topic :: Utilities
Classifier: Topic :: Scientific/Engineering :: Artificial Intelligence
Classifier: Topic :: System :: Distributed Computing
Classifier: Operating System :: OS Independent
Classifier: License :: OSI Approved :: MIT License
Classifier: Natural Language :: English
Requires-Python: >=3.8
License-File: LICENSE
Requires-Dist: requests>=2.32.3
Requires-Dist: tqdm>=4.67.1
Requires-Dist: websockets>=13.1
Dynamic: license-file
